{
  "entries": [
    {
      "jisCode": "14342",
      "oldZipCode": "25901",
      "zipCode": "2590100",
      "prefectureKana": "カナガワケン",
      "cityKana": "ナカグンニノミヤマチ",
      "townKana": "",
      "prefecture": "神奈川県",
      "city": "中郡二宮町",
      "town": "",
      "multipleZipCodes": "0",
      "numberedTown": "0",
      "hasChome": "0",
      "multipleTowns": "1",
      "updateFlag": "0",
      "updateReason": "0"
    },
    {
      "jisCode": "14361",
      "oldZipCode": "25901",
      "zipCode": "2590100",
      "prefectureKana": "カナガワケン",
      "cityKana": "アシガラカミグンナカイマチ",
      "townKana": "",
      "prefecture": "神奈川県",
      "city": "足柄上郡中井町",
      "town": "",
      "multipleZipCodes": "0",
      "numberedTown": "0",
      "hasChome": "0",
      "multipleTowns": "1",
      "updateFlag": "0",
      "updateReason": "0"
    }
  ]
}