{
  "entries": [
    {
      "jisCode": "26106",
      "oldZipCode": "600  ",
      "zipCode": "6008343",
      "prefectureKana": "キョウトフ",
      "cityKana": "キョウトシシモギョウク",
      "townKana": "ウエマツチョウ（ショウメンドオリニシノトウインニシイル、ニシノトウインドオリショウメンサガル）",
      "prefecture": "京都府",
      "city": "京都市下京区",
      "town": "植松町（正面通西洞院西入、西洞院通正面下る）",
      "multipleZipCodes": "0",
      "numberedTown": "0",
      "hasChome": "0",
      "multipleTowns": "0",
      "updateFlag": "0",
      "updateReason": "0"
    }
  ]
}