{
  "entries": [
    {
      "jisCode": "40382",
      "oldZipCode": "807  ",
      "zipCode": "8070042",
      "prefectureKana": "フクオカケン",
      "cityKana": "オンガグンミズマキマチ",
      "townKana": "ヨシダ",
      "prefecture": "福岡県",
      "city": "遠賀郡水巻町",
      "town": "吉田",
      "multipleZipCodes": "0",
      "numberedTown": "0",
      "hasChome": "0",
      "multipleTowns": "1",
      "updateFlag": "0",
      "updateReason": "0"
    },
    {
      "jisCode": "40382",
      "oldZipCode": "807  ",
      "zipCode": "8070042",
      "prefectureKana": "フクオカケン",
      "cityKana": "オンガグンミズマキマチ",
      "townKana": "ヨシダダンチ",
      "prefecture": "福岡県",
      "city": "遠賀郡水巻町",
      "town": "吉田団地",
      "multipleZipCodes": "0",
      "numberedTown": "0",
      "hasChome": "0",
      "multipleTowns": "1",
      "updateFlag": "0",
      "updateReason": "0"
    }
  ]
}