{
  "entries": [
    {
      "jisCode": "07521",
      "oldZipCode": "96377",
      "zipCode": "9637754",
      "prefectureKana": "フクシマケン",
      "cityKana": "タムラグンミハルマチ",
      "townKana": "エゲノコシ",
      "prefecture": "福島県",
      "city": "田村郡三春町",
      "town": "恵下越",
      "multipleZipCodes": "0",
      "numberedTown": "0",
      "hasChome": "0",
      "multipleTowns": "1",
      "updateFlag": "0",
      "updateReason": "0"
    },
    {
      "jisCode": "07521",
      "oldZipCode": "96377",
      "zipCode": "9637754",
      "prefectureKana": "フクシマケン",
      "cityKana": "タムラグンミハルマチ",
      "townKana": "ケハイザカ",
      "prefecture": "福島県",
      "city": "田村郡三春町",
      "town": "化粧坂",
      "multipleZipCodes": "0",
      "numberedTown": "0",
      "hasChome": "0",
      "multipleTowns": "1",
      "updateFlag": "0",
      "updateReason": "0"
    },
    {
      "jisCode": "07521",
      "oldZipCode": "96377",
      "zipCode": "9637754",
      "prefectureKana": "フクシマケン",
      "cityKana": "タムラグンミハルマチ",
      "townKana": "コウシンザカ",
      "prefecture": "福島県",
      "city": "田村郡三春町",
      "town": "庚申坂",
      "multipleZipCodes": "0",
      "numberedTown": "0",
      "hasChome": "0",
      "multipleTowns": "1",
      "updateFlag": "0",
      "updateReason": "0"
    },
    {
      "jisCode": "07521",
      "oldZipCode": "96377",
      "zipCode": "9637754",
      "prefectureKana": "フクシマケン",
      "cityKana": "タムラグンミハルマチ",
      "townKana": "シケンチョウ",
      "prefecture": "福島県",
      "city": "田村郡三春町",
      "town": "四軒丁",
      "multipleZipCodes": "0",
      "numberedTown": "0",
      "hasChome": "0",
      "multipleTowns": "1",
      "updateFlag": "0",
      "updateReason": "0"
    },
    {
      "jisCode": "07521",
      "oldZipCode": "96377",
      "zipCode": "9637754",
      "prefectureKana": "フクシマケン",
      "cityKana": "タムラグンミハルマチ",
      "townKana": "シンマチ",
      "prefecture": "福島県",
      "city": "田村郡三春町",
      "town": "新町",
      "multipleZipCodes": "0",
      "numberedTown": "0",
      "hasChome": "0",
      "multipleTowns": "1",
      "updateFlag": "0",
      "updateReason": "0"
    },
    {
      "jisCode": "07521",
      "oldZipCode": "96377",
      "zipCode": "9637754",
      "prefectureKana": "フクシマケン",
      "cityKana": "タムラグンミハルマチ",
      "townKana": "バングミ",
      "prefecture": "福島県",
      "city": "田村郡三春町",
      "town": "番組",
      "multipleZipCodes": "0",
      "numberedTown": "0",
      "hasChome": "0",
      "multipleTowns": "1",
      "updateFlag": "0",
      "updateReason": "0"
    },
    {
      "jisCode": "07521",
      "oldZipCode": "96377",
      "zipCode": "9637754",
      "prefectureKana": "フクシマケン",
      "cityKana": "タムラグンミハルマチ",
      "townKana": "バングミガシラ",
      "prefecture": "福島県",
      "city": "田村郡三春町",
      "town": "番組頭",
      "multipleZipCodes": "0",
      "numberedTown": "0",
      "hasChome": "0",
      "multipleTowns": "1",
      "updateFlag": "0",
      "updateReason": "0"
    },
    {
      "jisCode": "07521",
      "oldZipCode": "96377",
      "zipCode": "9637754",
      "prefectureKana": "フクシマケン",
      "cityKana": "タムラグンミハルマチ",
      "townKana": "ユミマチ",
      "prefecture": "福島県",
      "city": "田村郡三春町",
      "town": "弓町",
      "multipleZipCodes": "0",
      "numberedTown": "0",
      "hasChome": "0",
      "multipleTowns": "1",
      "updateFlag": "0",
      "updateReason": "0"
    }
  ]
}