{
  "entries": [
    {
      "jisCode": "07208",
      "oldZipCode": "966  ",
      "zipCode": "9660814",
      "prefectureKana": "フクシマケン",
      "cityKana": "キタカタシ",
      "townKana": "オシミズ",
      "prefecture": "福島県",
      "city": "喜多方市",
      "town": "御清水",
      "multipleZipCodes": "0",
      "numberedTown": "0",
      "hasChome": "0",
      "multipleTowns": "1",
      "updateFlag": "0",
      "updateReason": "0"
    },
    {
      "jisCode": "07208",
      "oldZipCode": "966  ",
      "zipCode": "9660814",
      "prefectureKana": "フクシマケン",
      "cityKana": "キタカタシ",
      "townKana": "オシミズヒガシ",
      "prefecture": "福島県",
      "city": "喜多方市",
      "town": "御清水東",
      "multipleZipCodes": "0",
      "numberedTown": "0",
      "hasChome": "0",
      "multipleTowns": "1",
      "updateFlag": "0",
      "updateReason": "0"
    }
  ]
}